django_mqtt_bridge/__init__.py
django_mqtt_bridge/cli.py
django_mqtt_bridge/server.py
django_mqtt_bridge-0.4.5.dist-info/licenses/LICENSE
django_mqtt_bridge-0.4.5.dist-info/METADATA
django_mqtt_bridge-0.4.5.dist-info/WHEEL
django_mqtt_bridge-0.4.5.dist-info/entry_points.txt
django_mqtt_bridge-0.4.5.dist-info/top_level.txt
django_mqtt_bridge-0.4.5.dist-info/RECORD
